[
  {
    "file": "D:\\Coding\\Personal\\01-core-systems\\brand\\1-103、硬核品牌 决胜终端---张雪机车硬核品牌的18个关键步骤硬核案例.docx",
    "paragraphs": 208,
    "headings": [
      "第1步：消费者研究——洞察未被满足的需求",
      "一、理论工具",
      "二、方法模型",
      "三、品牌实践",
      "四、品牌案例",
      "五、品牌总结与借鉴",
      "第2步：竞争对手研究——寻找市场空隙",
      "一、理论工具",
      "二、方法模型",
      "三、品牌实践",
      "四、品牌案例",
      "五、品牌总结与借鉴",
      "第3步：市场环境研究——把握趋势机会",
      "一、理论工具",
      "二、方法模型",
      "三、品牌实践",
      "四、品牌案例",
      "五、品牌总结与借鉴",
      "第4步：品牌自身研究——挖掘核心能力",
      "一、理论工具",
      "二、方法模型",
      "三、品牌实践",
      "四、品牌案例",
      "五、品牌总结与借鉴",
      "第5步：品牌战略规划——明确发展方向",
      "一、理论工具",
      "二、方法模型",
      "三、品牌实践",
      "四、品牌案例",
      "五、品牌总结与借鉴",
      "第6步：品牌核心价值提炼——打造品牌DNA",
      "一、理论工具",
      "二、方法模型",
      "三、品牌实践",
      "四、品牌案例",
      "五、品牌总结与借鉴",
      "第7步：品牌定位——占据心智位置",
      "一、理论工具",
      "二、方法模型",
      "三、品牌实践",
      "四、品牌案例",
      "五、品牌总结与借鉴",
      "第8步：品牌命名——创造独特的识别符号",
      "一、理论工具",
      "二、方法模型",
      "三、品牌实践",
      "四、品牌案例",
      "五、品牌总结与借鉴",
      "第9步：品牌主张与口号——提炼沟通核心",
      "一、理论工具",
      "二、方法模型",
      "三、品牌实践",
      "四、品牌案例",
      "五、品牌总结与借鉴",
      "第10步：品牌个性塑造——赋予品牌人格",
      "一、理论工具",
      "二、方法模型",
      "三、品牌实践",
      "四、品牌案例",
      "五、品牌总结与借鉴",
      "第11步：品牌设计——视觉化呈现",
      "一、理论工具",
      "二、方法模型",
      "三、品牌实践",
      "四、品牌案例",
      "五、品牌总结与借鉴",
      "第12步：品牌传播——整合营销沟通",
      "一、理论工具",
      "二、方法模型",
      "三、品牌实践",
      "四、品牌案例",
      "五、品牌总结与借鉴",
      "第13步：品牌营销——价值转化为销售",
      "一、理论工具",
      "二、方法模型",
      "三、品牌实践",
      "四、品牌案例",
      "五、品牌总结与借鉴",
      "第14步：品牌活动——创造互动体验",
      "一、理论工具"
    ],
    "tables": 0,
    "chars": 21817
  },
  {
    "file": "D:\\Coding\\Personal\\01-core-systems\\brand\\1-121、品牌复盘 决胜终端——小米公司品牌创新与改进咨询报告.docx",
    "paragraphs": 224,
    "headings": [
      "第一阶段：品牌调研与洞察（第1-4步）",
      "第1步：消费者研究——洞察未被满足的需求",
      "一、大师理论",
      "二、方法模型",
      "三、小米公司品牌成果与错误",
      "四、小米公司品牌创新与改进方案建议",
      "五、品牌创新与改进的经验与教训借鉴",
      "第2步：竞争对手研究——寻找市场空隙",
      "一、大师理论",
      "二、方法模型",
      "三、小米公司品牌成果与错误",
      "四、小米公司品牌创新与改进方案建议",
      "五、品牌创新与改进的经验与教训借鉴",
      "第3步：市场环境研究——把握趋势机会",
      "一、大师理论",
      "二、方法模型",
      "三、小米公司品牌成果与错误",
      "四、小米公司品牌创新与改进方案建议",
      "五、品牌创新与改进的经验与教训借鉴",
      "第4步：品牌自身研究——挖掘核心能力",
      "一、大师理论",
      "二、方法模型",
      "三、小米公司品牌成果与错误",
      "四、小米公司品牌创新与改进方案建议",
      "五、品牌创新与改进的经验与教训借鉴",
      "第二阶段：品牌定位与策略制定（第5-11步）",
      "第5步：品牌战略规划——明确发展方向",
      "一、大师理论",
      "二、方法模型",
      "三、小米公司品牌成果与错误",
      "四、小米公司品牌创新与改进方案建议",
      "五、品牌创新与改进的经验与教训借鉴",
      "第6步：品牌核心价值提炼——打造品牌DNA",
      "一、大师理论",
      "二、方法模型",
      "三、小米公司品牌成果与错误",
      "四、小米公司品牌创新与改进方案建议",
      "五、品牌创新与改进的经验与教训借鉴",
      "第7步：品牌定位——占据心智位置",
      "一、大师理论",
      "二、方法模型",
      "三、小米公司品牌成果与错误",
      "四、小米公司品牌创新与改进方案建议",
      "五、品牌创新与改进的经验与教训借鉴",
      "第8步：品牌命名——创造独特的识别符号",
      "一、大师理论",
      "二、方法模型",
      "三、小米公司品牌成果与错误",
      "四、小米公司品牌创新与改进方案建议",
      "五、品牌创新与改进的经验与教训借鉴",
      "第9步：品牌主张与口号——提炼沟通核心",
      "一、大师理论",
      "二、方法模型",
      "三、小米公司品牌成果与错误",
      "四、小米公司品牌创新与改进方案建议",
      "五、品牌创新与改进的经验与教训借鉴",
      "第10步：品牌个性塑造——赋予品牌人格",
      "一、大师理论",
      "二、方法模型",
      "三、小米公司品牌成果与错误",
      "四、小米公司品牌创新与改进方案建议",
      "五、品牌创新与改进的经验与教训借鉴",
      "第11步：品牌设计——视觉化呈现",
      "一、大师理论",
      "二、方法模型",
      "三、小米公司品牌成果与错误",
      "四、小米公司品牌创新与改进方案建议",
      "五、品牌创新与改进的经验与教训借鉴",
      "第12步：品牌传播——传递核心价值",
      "一、大师理论",
      "二、方法模型",
      "三、小米公司品牌成果与错误",
      "四、小米公司品牌创新与改进方案建议",
      "五、品牌创新与改进的经验与教训借鉴",
      "第13步：品牌渠道——构建高效触达网络",
      "一、大师理论",
      "二、方法模型",
      "三、小米公司品牌成果与错误",
      "四、小米公司品牌创新与改进方案建议",
      "五、品牌创新与改进的经验与教训借鉴"
    ],
    "tables": 0,
    "chars": 31467
  },
  {
    "file": "D:\\Coding\\Personal\\01-core-systems\\brand\\1-45、硬核品牌 决胜终端---汉庭酒店品牌18个关键步骤硬核案例案例研究报告.docx.docx",
    "paragraphs": 286,
    "headings": [
      "第一阶段：品牌调研与洞察（第1-4步）",
      "第1步：消费者研究——洞察未被满足的需求",
      "一、大师理论",
      "二、方法模型",
      "三、品牌实践",
      "四、案例分析",
      "五、总结与借鉴",
      "第2步：竞争对手研究——寻找市场空隙",
      "一、大师理论",
      "二、方法模型",
      "三、品牌实践",
      "四、案例分析",
      "五、总结与借鉴",
      "第3步：市场环境研究——把握趋势机会",
      "一、大师理论",
      "二、方法模型",
      "三、品牌实践",
      "四、案例分析",
      "五、总结与借鉴",
      "第4步：品牌自身研究——挖掘核心能力",
      "一、大师理论",
      "二、方法模型",
      "三、品牌实践",
      "四、案例分析",
      "五、总结与借鉴",
      "第二阶段：品牌定位与策略制定（第5-11步）",
      "第5步：品牌战略规划——明确发展方向",
      "一、大师理论",
      "二、方法模型",
      "三、品牌实践",
      "四、案例分析",
      "五、总结与借鉴",
      "第6步：品牌核心价值提炼——打造品牌DNA",
      "一、大师理论",
      "二、方法模型",
      "三、品牌实践",
      "四、案例分析",
      "五、总结与借鉴",
      "第7步：品牌定位——占据心智位置",
      "一、大师理论",
      "二、方法模型",
      "三、品牌实践",
      "四、案例分析",
      "五、总结与借鉴",
      "第8步：品牌命名——创造独特的识别符号",
      "一、大师理论",
      "二、方法模型",
      "三、品牌实践",
      "四、案例分析",
      "五、总结与借鉴",
      "第9步：品牌主张与口号——提炼沟通核心",
      "一、大师理论",
      "二、方法模型",
      "三、品牌实践",
      "四、案例分析",
      "五、总结与借鉴",
      "第10步：品牌个性塑造——赋予品牌人格",
      "一、大师理论",
      "二、方法模型",
      "三、品牌实践",
      "四、案例分析",
      "五、总结与借鉴",
      "第11步：品牌设计——视觉化呈现品牌内核",
      "一、大师理论",
      "二、方法模型",
      "三、品牌实践",
      "四、案例分析",
      "五、总结与借鉴",
      "第三阶段：品牌落地与执行（第12-16步）",
      "第12步：品牌传播——整合营销沟通，放大品牌心智",
      "一、大师理论",
      "二、方法模型",
      "三、品牌实践",
      "四、案例分析",
      "五、总结与借鉴",
      "第13步：品牌营销——价值转化为销售，实现品效合一",
      "一、大师理论",
      "二、方法模型",
      "三、品牌实践",
      "四、案例分析"
    ],
    "tables": 0,
    "chars": 32506
  },
  {
    "file": "D:\\Coding\\Personal\\01-core-systems\\brand\\1-60、硬核品牌 决胜终端---胖东来硬核品牌的18个关键步骤硬核案例.docx",
    "paragraphs": 132,
    "headings": [
      "第1步：消费者研究——洞察未被满足的需求",
      "一、理论工具",
      "二、方法模型",
      "三、品牌实践",
      "四、品牌案例",
      "五、品牌总结与借鉴",
      "第2步：竞争对手研究——寻找市场空隙",
      "一、理论工具",
      "二、方法模型",
      "三、品牌实践",
      "四、品牌案例",
      "五、品牌总结与借鉴",
      "第3步：市场环境研究——把握趋势机会",
      "一、理论工具",
      "二、方法模型",
      "三、品牌实践",
      "四、品牌案例",
      "五、品牌总结与借鉴",
      "第4步：品牌自身研究——挖掘核心能力",
      "一、理论工具",
      "二、方法模型",
      "三、品牌实践",
      "四、品牌案例",
      "五、品牌总结与借鉴",
      "第5步：品牌战略规划——明确发展方向",
      "一、理论工具",
      "二、方法模型",
      "三、品牌实践",
      "四、品牌案例",
      "五、品牌总结与借鉴",
      "第6步：品牌核心价值提炼——打造品牌DNA",
      "一、理论工具",
      "二、方法模型",
      "三、品牌实践",
      "四、品牌案例",
      "五、品牌总结与借鉴",
      "第7步：品牌定位——占据心智位置",
      "一、理论工具",
      "二、方法模型",
      "三、品牌实践",
      "四、品牌案例",
      "五、品牌总结与借鉴",
      "第8步：品牌命名——创造独特的识别符号",
      "一、理论工具",
      "二、方法模型",
      "三、品牌实践",
      "四、品牌案例",
      "五、品牌总结与借鉴",
      "第9步：品牌主张与口号——提炼沟通核心",
      "一、理论工具",
      "二、方法模型",
      "三、品牌实践",
      "四、品牌案例",
      "五、品牌总结与借鉴",
      "第10步：品牌个性塑造——赋予品牌人格",
      "一、理论工具",
      "二、方法模型",
      "三、品牌实践",
      "四、品牌案例",
      "五、品牌总结与借鉴",
      "第11步：品牌设计——视觉化呈现",
      "一、理论工具",
      "二、方法模型",
      "三、品牌实践",
      "四、品牌案例",
      "五、品牌总结与借鉴",
      "第12步：品牌传播——整合营销沟通",
      "一、理论工具",
      "二、方法模型",
      "三、品牌实践",
      "四、品牌案例"
    ],
    "tables": 0,
    "chars": 16834
  },
  {
    "file": "D:\\Coding\\Personal\\01-core-systems\\brand\\1-90、硬核品牌 决胜终端---沃尔玛优质客户服务案例研究报告.docx",
    "paragraphs": 221,
    "headings": [
      "第一阶段：服务调研与需求洞察（第1-4步）",
      "第1步：客户需求研究——挖掘未被满足的服务痛点",
      "第2步：同行服务研究——寻找服务差异化空隙",
      "第3步：服务环境研究——把握行业服务趋势与政策导向",
      "第4步：自身服务研究——梳理现有优势与短板",
      "第二阶段：服务定位与体系制定（第5-11步）",
      "第5步：服务战略规划——明确服务发展核心方向",
      "第6步：服务核心价值提炼——打造服务核心竞争力",
      "第7步：服务定位——占据客户心智中的服务高地",
      "第8步：服务标准制定——明确服务流程与执行规范",
      "第9步：服务口号与承诺——提炼沟通核心主张",
      "第10步：服务团队塑造——打造专业且有温度的服务人格",
      "第11步：服务场景设计——可视化、场景化呈现服务细节",
      "第三阶段：服务落地与执行（第12-16步）",
      "第12步：服务传递——全渠道整合服务触达",
      "第13步：服务转化——将服务价值转化为客户忠诚",
      "第14步：服务互动——创造有记忆点的客户体验",
      "第15步：服务公关——妥善处理客诉，塑造服务美誉度",
      "第16步：服务跟进——深化客户关系，提升复购与转介绍",
      "第四阶段：服务优化与升级（第17-18步）",
      "第17步：服务管理——系统化运营，沉淀服务资产",
      "第18步：服务升级——持续创新与活化",
      "第2步：同行服务研究——寻找服务差异化空隙",
      "第3步：服务环境研究——把握行业服务趋势与政策导向",
      "第4步：自身服务研究——梳理现有优势与短板",
      "第二阶段：服务定位与体系制定（第5-11步）",
      "第5步：服务战略规划——明确服务发展核心方向",
      "第6步：服务核心价值提炼——打造服务核心竞争力",
      "第7步：服务定位——占据客户心智中的服务高地",
      "第8步：服务标准制定——明确服务流程与执行规范",
      "第9步：服务口号与承诺——提炼沟通核心主张",
      "第10步：服务团队塑造——打造专业且有温度的服务人格",
      "第11步：服务场景设计——可视化、场景化呈现服务细节",
      "第三阶段：服务落地与执行（第12-16步）",
      "第12步：服务传递——全渠道整合服务触达",
      "第13步：服务转化——将服务价值转化为客户忠诚",
      "第14步：服务互动——创造有记忆点的客户体验",
      "第15步：服务公关——妥善处理客诉，塑造服务美誉度",
      "第16步：服务跟进——深化客户关系，提升复购与转介绍",
      "第四阶段：服务优化与升级（第17-18步）",
      "第17步：服务管理——系统化运营，沉淀服务资产",
      "第18步：服务升级——持续创新与活化"
    ],
    "tables": 0,
    "chars": 34535
  },
  {
    "file": "D:\\Coding\\Personal\\01-core-systems\\brand\\1-94、硬核品牌 决胜终端---雅兰硬核品牌的18个关键步骤硬核案例.docx",
    "paragraphs": 151,
    "headings": [
      "第一部分：雅兰品牌18个关键步骤复盘",
      "第1步：消费者研究——洞察未被满足的需求",
      "一、理论工具",
      "二、方法模型",
      "三、品牌实践",
      "四、品牌案例",
      "五、品牌总结与借鉴",
      "第2步：竞争对手研究——寻找市场空隙",
      "一、理论工具",
      "二、方法模型",
      "三、品牌实践",
      "四、品牌案例",
      "五、品牌总结与借鉴",
      "第3步：市场环境研究——把握趋势机会",
      "一、理论工具",
      "二、方法模型",
      "三、品牌实践",
      "四、品牌案例",
      "五、品牌总结与借鉴",
      "第4步：品牌自身研究——挖掘核心能力",
      "一、理论工具",
      "二、方法模型",
      "三、品牌实践",
      "四、品牌案例",
      "五、品牌总结与借鉴",
      "第5步：品牌战略规划——明确发展方向",
      "一、理论工具",
      "二、方法模型",
      "三、品牌实践",
      "四、品牌案例",
      "五、品牌总结与借鉴",
      "第6步：品牌核心价值提炼——打造品牌DNA",
      "一、理论工具",
      "二、方法模型",
      "三、品牌实践",
      "四、品牌案例",
      "五、品牌总结与借鉴",
      "第7步：品牌定位——占据心智位置",
      "一、理论工具",
      "二、方法模型",
      "三、品牌实践",
      "四、品牌案例",
      "五、品牌总结与借鉴",
      "第8步：品牌命名——创造独特的识别符号",
      "一、理论工具",
      "二、方法模型",
      "三、品牌实践",
      "四、品牌案例",
      "五、品牌总结与借鉴",
      "第9步：品牌主张与口号——提炼沟通核心",
      "一、理论工具",
      "二、方法模型",
      "三、品牌实践",
      "四、品牌案例",
      "五、品牌总结与借鉴",
      "第10步：品牌个性塑造——赋予品牌人格",
      "一、理论工具",
      "二、方法模型",
      "三、品牌实践",
      "四、品牌案例",
      "五、品牌总结与借鉴",
      "第11步：品牌设计——视觉化呈现",
      "一、理论工具",
      "二、方法模型",
      "三、品牌实践",
      "四、品牌案例",
      "五、品牌总结与借鉴",
      "第12步：品牌传播——整合营销沟通",
      "一、理论工具",
      "二、方法模型",
      "三、品牌实践",
      "四、品牌案例",
      "五、品牌总结与借鉴",
      "第13步：品牌营销——价值转化为销售",
      "一、理论工具",
      "二、方法模型",
      "三、品牌实践",
      "四、品牌案例",
      "五、品牌总结与借鉴",
      "第14步：品牌活动——创造互动体验"
    ],
    "tables": 0,
    "chars": 16185
  },
  {
    "file": "D:\\Coding\\Personal\\01-core-systems\\brand\\1-99、硬核品牌 决胜终端---元气森林硬核品牌的18个关键步骤硬核案例.docx",
    "paragraphs": 766,
    "headings": [
      "消费者研究——洞察未被满足的需求",
      "🧠 大师理论：从“产品属性”转向“用户任务”",
      "🛠️ 方法模型：系统化洞察工具箱",
      "🚀 品牌实践：新兴品牌如何发现“空白地带”",
      "📊 案例分析：待办任务理论在元气森林的具体实践",
      "💡 总结与借鉴：给新兴品牌的启示",
      "竞争对手研究——寻找市场空隙",
      "🧠 大师理论：从“竞争结构”到“价值创新”",
      "🛠️ 方法模型：可视化竞争格局，定位战略空隙",
      "🚀 品牌实践：新兴品牌如何“钻空子”",
      "📊 深度案例：元气森林的“空隙狙击”四步法",
      "💎 总结与借鉴",
      "市场环境研究——把握趋势机会",
      "核心理论：系统化的趋势雷达",
      "趋势扫描与机会评估实战",
      "案例复盘：趋势驱动的品牌崛起",
      "总结与借鉴：从“看见趋势”到“驾驭趋势”",
      "品牌自身研究——挖掘核心能力",
      "🧠 理论基石：从资源到竞争力的系统锻造",
      "⚙️ 实践路径：新兴品牌的能力锻造地图",
      "💎 总结与借鉴：核心能力是品牌生长的根",
      "品牌战略规划——明确发展方向",
      "大师理论：从波特竞争战略到品牌愿景",
      "方法模型：从OGSM框架到品牌屋",
      "品牌实践：新兴品牌的战略选择逻辑",
      "案例分析：元气森林与SHEIN的战略路径",
      "元气森林：聚焦差异化的“无糖专门家”纵深战略",
      "SHEIN：数字化驱动的“成本领先+差异化”混合战略",
      "总结与借鉴：如何为新兴品牌规划战略方向",
      "品牌核心价值提炼——打造品牌DNA",
      "大师理论精要：品牌价值的“三重结构”与系统性原则",
      "价值三重奏：",
      "提炼的核心原则：",
      "方法模型：从抽象价值到具体体系的构建工具",
      "品牌实践：元气森林与SHEIN的DNA炼成记",
      "• 元气森林：从“功能痛点”到“元气生活”的价值升华",
      "• SHEIN：用“系统效率”兑现“时尚平权”的价值承诺",
      "案例分析：从“产品卖点”到“品牌信仰”的飞跃",
      "总结与借鉴：如何炼就历久弥新的品牌DNA",
      "品牌定位——占据心智位置",
      "大师理论+方法模型：定位的底层逻辑与系统工具",
      "核心理论：心智战争与品类占位",
      "核心模型：定位钻石模型",
      "洞察工具：心智地图",
      "品牌实践+案例分析：新兴品牌如何钉入心智",
      "案例一：元气森林——定义“好喝的无糖”，占领品类制高点",
      "案例二：SHEIN——开创“超快时尚电商”，重塑行业认知",
      "总结和借鉴：定位是系统工程，关键在“聚焦”与“配称”",
      "品牌命名——创造独特的识别符号",
      "大师理论：命名是成本、召唤与投资的科学",
      "方法模型：从“音形意”到系统评估的决策工具",
      "品牌实践：元气森林与SHEIN的命名逻辑",
      "案例分析：从创意到验证的完整流程闭环",
      "总结与借鉴：可复制的命名方法论",
      "品牌主张与口号——提炼沟通核心",
      "核心理论框架：从“言说”到“情感连接”",
      "方法模型：系统化构建与精准提炼",
      "品牌实践案例分析：元气森林与SHEIN的沟通核心",
      "总结与借鉴：给新兴品牌的行动路线",
      "品牌个性塑造——赋予品牌人格",
      "大师理论：从“角色原型”到“关系深度”",
      "方法模型：系统化的人格塑造路径",
      "品牌原型选择路径：",
      "品牌实践：元气森林与SHEIN如何“活”起来",
      "总结与借鉴",
      "品牌设计——视觉化呈现",
      "🧠 大师理论：从“格式塔”整体到“视觉锤”穿透",
      "格式塔心理学：强调整体性认知",
      "视觉锤理论：创造心智穿透点",
      "📐 方法模型：VIS系统化构建与色彩情感化应用",
      "🥤 品牌实践：元气森林的“伪日系”系统与SHEIN的“数据驱动”视觉",
      "💡 总结与借鉴：新兴品牌视觉突围的五大关键",
      "品牌传播——整合营销沟通",
      "大师理论：整合营销传播 (Integrated Marketing Communications, IMC)",
      "方法模型：AISAS模型与品牌接触点管理",
      "品牌实践：元气森林的整合传播与数据闭环",
      "统一声音，跨触点整合",
      "数据驱动的AISAS旅程管理",
      "关键接触点的数字化赋能",
      "案例分析：从“口号级钉子”到“整合级锤子”"
    ],
    "tables": 7,
    "chars": 46156
  },
  {
    "file": "D:\\Coding\\Personal\\01-core-systems\\brand\\B-1、课前学习资料：降龙十八掌-18个关键步骤打造行业知名品牌(方法篇)(1).docx",
    "paragraphs": 119,
    "headings": [
      "降龙18掌-18步复盘完美品牌",
      "暨复盘知名品牌的18个关键步骤",
      "品牌复盘",
      "品牌创新18步复盘",
      "品牌 18 步｜正宗降龙十八掌品牌复盘",
      "品牌创新18步复盘实战训练大纲",
      "打造完美品牌18步概述",
      "品牌创新18步复盘实战训练操作手册",
      "消费者研究——洞察未被满足的需求",
      "竞争对手研究——寻找市场空隙",
      "市场环境研究——把握趋势机会",
      "品牌自身研究——挖掘核心能力",
      "品牌战略规划——明确发展方向",
      "品牌核心价值提炼——打造独特品牌DNA",
      "品牌定位——占领用户心智",
      "品牌命名——创造独特的识别符号",
      "品牌主张与口号——搭建沟通核心",
      "品牌个性塑造——赋予人格化特征",
      "品牌设计——实现可视化呈现",
      "品牌传播——实现高效触达",
      "品牌营销与渠道布局——打通落地路径",
      "第14步：品牌活动——创造互动体验",
      "第15步：品牌公关——塑造美誉度",
      "第16步：品牌服务与体验优化——强化用户粘性",
      "第17步：品牌管理与资产积累——实现长期增值",
      "第17步：品牌管理与品牌危机管理——守护品牌声誉",
      "第18步：品牌迭代升级——适配时代发展",
      "第18步：品牌迭代升级与品牌可持续发展——构建长期竞争力",
      "附：十八步18步品牌拆解",
      "品牌复盘研究院首席顾问李院长介绍"
    ],
    "tables": 24,
    "chars": 3082
  },
  {
    "file": "D:\\Coding\\Personal\\01-core-systems\\brand\\B-2、课前学习资料：降龙十八掌-18个关键步骤打造行业知名品牌(工具篇).docx",
    "paragraphs": 404,
    "headings": [
      "降龙18掌--品牌复盘18步",
      "知名品牌是如何通过18步一步一步被创造出来的？",
      "品牌复盘",
      "第一阶段：品牌调研与洞察（第1-4步）",
      "第1步：消费者研究——洞察未被满足的需求",
      "第2步：竞争对手研究——寻找市场空隙",
      "第3步：市场环境研究——把握趋势机会",
      "第4步：品牌自身研究——挖掘核心能力",
      "第二阶段：品牌定位与策略制定（第5-11步）",
      "第5步：品牌战略规划——明确发展方向",
      "第6步：品牌命名——创造独特的识别符号",
      "第7步：品牌定位——占据消费者心智",
      "第8步：核心价值提炼——打造品牌灵魂",
      "第9步：品牌口号设计——传递核心价值",
      "第10步：品牌视觉形象设计——打造视觉识别符号",
      "第11步：品牌架构梳理——实现协同发展",
      "第三阶段：品牌落地与执行（第12-15步）",
      "第12步：产品创新——承载品牌核心价值",
      "第13步：渠道布局——打通品牌触达路径",
      "第14步：品牌传播——放大品牌影响力",
      "第15步：终端体验——强化品牌认知",
      "第四阶段：品牌持续升级（第16-18步）",
      "第16步：品牌监测——把握品牌发展动态",
      "第17步：品牌优化——迭代升级品牌竞争力",
      "第18步：品牌延伸——拓展品牌边界与价值",
      "品牌复盘研究院首席顾问李院长介绍"
    ],
    "tables": 3,
    "chars": 52925
  },
  {
    "file": "D:\\Coding\\Personal\\01-core-systems\\brand\\B-3、课前学习资料：降龙十八掌-18个关键步骤打造行业知名品牌(陪跑篇)(1).docx",
    "paragraphs": 189,
    "headings": [
      "降龙18掌-18步复盘完美品牌",
      "暨复盘知名品牌的18个关键步骤",
      "品牌复盘",
      "降龙18掌--品牌复盘18 步",
      "知名品牌是如何通过18步一步一步被创造出来的？",
      "第一阶段：品牌调研与洞察（第1-4步）",
      "第1步品牌复盘：消费者研究——洞察未被满足的需求",
      "第2步品牌复盘：竞争对手研究——寻找市场空隙",
      "第3步品牌复盘：市场环境研究——把握趋势机会",
      "第4步品牌复盘：品牌自身研究——挖掘核心能力",
      "第二阶段：品牌定位与策略制定（第5-11步）",
      "第5步品牌复盘：品牌战略规划——明确发展方向",
      "第6步品牌复盘：品牌命名——创造独特的识别符号",
      "第7步品牌复盘：品牌定位——占据心智位置",
      "第8步品牌复盘：品牌核心价值提炼——打造品牌DNA",
      "第9步品牌复盘：品牌主张与口号——提炼沟通核心",
      "第10步品牌复盘：品牌个性塑造——赋予品牌人格",
      "第11步品牌复盘：品牌设计——视觉化呈现",
      "第三阶段：品牌落地与执行（第12-16步）",
      "第12步品牌复盘：品牌传播——整合营销沟通",
      "第13步品牌复盘：品牌营销——价值转化为销售",
      "第14步品牌复盘：品牌活动——创造互动体验",
      "第15步品牌复盘：品牌公关——塑造美誉度",
      "第16步品牌复盘：品牌服务——深化客户关系",
      "第四阶段：品牌管理与升级（第17-18步）",
      "第17步品牌复盘：品牌管理——系统化运营",
      "第18步品牌复盘：品牌升级——持续创新与活化",
      "总结：品牌创新的系统工程",
      "30 天品牌启动执行排期表（极简可直接落地）",
      "第 1-7 天：调研与定位（定方向）",
      "第 8-14 天：品牌符号与基础物料（定形象）",
      "第 15-21 天：落地准备（可上线）",
      "第 22-28 天：正式启动 + 传播（见效果）",
      "第一场品牌活动执行",
      "第一轮数据复盘：曝光、咨询、转化",
      "第 29-30 天：复盘与优化（定长期）",
      "30 天品牌启动执行排期表（含工具 + 方法）",
      "品牌复盘研究院首席顾问李院长介绍"
    ],
    "tables": 4,
    "chars": 7023
  }
]